{
  "data": [
    {
      "id": 1,
      "group": "learning",
      "icon": "pelajaran-1.png",
      "name": "Matematika"
    },
    {
      "id": 2,
      "group": "learning",
      "icon": "pelajaran-2.png",
      "name": "IPA"
    },
    {
      "id": 3,
      "group": "learning",
      "icon": "pelajaran-3.png",
      "name": "IPS"
    },
    {
      "id": 4,
      "group": "learning",
      "icon": "pelajaran-4.png",
      "name": "Agama"
    },
    {
      "id": 5,
      "group": "learning",
      "icon": "pelajaran-5.png",
      "name": "PKN"
    },
    {
      "id": 6,
      "group": "learning",
      "icon": "pelajaran-6.png",
      "name": "Seni Budaya"
    },
    {
      "id": 7,
      "group": "learning",
      "icon": "pelajaran-7.png",
      "name": "Olahraga"
    },
    {
      "id": 8,
      "group": "learning",
      "icon": "pelajaran-8.png",
      "name": "B. Indonesia"
    },
    {
      "id": 9,
      "group": "learning",
      "icon": "pelajaran-9.png",
      "name": "B. Inggris"
    },
    {
      "id": 10,
      "group": "role",
      "icon": "role-1.png",
      "img": "main-role.png",
      "name": "Kesatria",
      "active": true,
      "feature": {
        "about": "Kesatria pemberani yang mengayunkan pedangnya untuk melindungi yang lemah dan melawan kejahatan.",
        "advantage": "Kamu akan mendapatkan tambahan kekuatan dan keberanian yang luar biasa",
        "purpose": "Melindungi yang lemah, dan Menumpas yang jahat"
      }
    },
    {
      "id": 11,
      "group": "role",
      "icon": "role-2.png",
      "img": "main-role-2.png",
      "name": "Pengrajin",
      "active": false,
      "feature": {
        "about": "Pengrajin merupakan orang yang ahli dalam membuat sesuatu yang menakjubkan seperti senjata dan alat lainnya",
        "advantage": "Kamu akan mendapatkan tambahan imajinasi dan fokus yang luar biasa",
        "purpose": "Membuat sesuatu yang tidak mungkin menjadi mungkin"
      }
    },
    {
      "id": 12,
      "group": "role",
      "icon": "role-3.png",
      "img": "main-role-3.png",
      "name": "Penyihir",
      "active": false,
      "feature": {
        "about": "Penyihir bertugas untuk membentuk ramuan obat yang mampu memberikan support kepada kesatria dan pertahanan yang kokoh",
        "advantage": "Kamu akan mendapatkan tambahan kecerdasan dan empati yang luar biasa",
        "purpose": "Mempelajari segala sesuatu yang ada didunia"
      }
    },
    {
      "id": 13,
      "group": "course",
      "img": "course-1.png",
      "title": "IPA",
      "description" : "Belajar membuat gambar 2d sampai mewarnai gambar tersebut",
      "category" : "kursus",
      "active": false,
      "text" : "Ilmu alam atau ilmu pengetahuan alam disingkat IPA (bahasa Inggris: natural science) adalah istilah yang digunakan yang merujuk pada rumpun ilmu di mana objeknya adalah benda-benda alam dengan hukum-hukum yang pasti dan umum, berlaku kapan pun dan di mana pun. Orang yang menekuni bidang ilmu pengetahuan alam disebut sebagai Saintis. <br>Sains (science) diambil dari kata latin scientia yang arti harfiahnya adalah pengetahuan. Sund dan Trowbribge merumuskan bahwa Sains merupakan kumpulan pengetahuan dan proses. Sedangkan Kuslan Stone menyebutkan bahwa Sains adalah kumpulan pengetahuan dan cara-cara untuk mendapatkan dan mempergunakan pengetahuan itu. Sains merupakan produk dan proses yang tidak dapat dipisahkan. ",
      "level" : "junior",
      "feature": {
        "rating": 5,
        "users" : 20,
        "age": 6
      }
    },
    {
      "id": 14,
      "group": "course",
      "img": "course-2.png",
      "title": "Matematika",
      "description" : "Melatih logika dan perhitungan dalam dunia matematika. Belajar dari pemula sampai mahir",
      "category" : "kursus",
      "active": false,
      "text" : "Matematika (dari bahasa Yunani: μαθημα - mathēma, pengetahuan, pemikiran, pembelajaran) atau sebelumnya disebut ilmu hisab adalah ilmu yang mempelajari besaran, struktur, ruang, dan perubahan. Para matematikawan merangkai dan menggunakan berbagai pola, kemudian menggunakannya untuk merumuskan konjektur baru, dan membangun kebenaran melalui metode deduksi yang ketat diturunkan dari aksioma-aksioma dan definisi-definisi yang bersesuaian. <br>Terjadi perdebatan apakah objek-objek matematika seperti bilangan dan titik sudah ada di semesta, ataukah ditemukan dan diciptakan manusia. Pengkajian logis mengenai bentuk, susunan, besaran, dan konsep-konsep yang berkaitan, matematika sering kali dikelompokkan ke dalam tiga bidang: aijabar, analisis, dan geometri. Walaupun demikian, tidak dapat dibuat pembagian yang jelas karena cabang-cabang ini telah bercampur baur. Pada dasarnya aijabar melibatkan bilangan dan pengabstrakannya. Analisis melibatkan kekontinuan dan limit, sedangkan geometri membahas bentuk dan konsep-konsep yang berkaitan; sains didasarkan atas postulat yang dapat menurunkan kesimpulan yang diperlukan dari asumsi tertentu.",
      "level" : "senior",
      "feature": {
        "rating": 4,
        "users" : 13,
        "age": 6
      }
    },
    {
      "id": 15,
      "group": "course",
      "img": "course-3.png",
      "title": "Seni Budaya",
      "description" : "Melatih ilmu kesenian pada tingkat junior dengan mengajarkan dasar yang sangat baik",
      "category" : "kursus",
      "active": false,
      "text" : "Kata “seni” dalam bahasa Indonesia mempunyai riwayat peristilahan yang tidak sederhana, baik dipandang dari segi terminologis maupun etimologisnya. Hal tersebut mulanya disebabkan karena ketiadaan padanan istilah yang pas dalam bahasa Indonesia/Melayu untuk konsep art dalam bahasa Inggris atau kunst dalam bahasa Belanda. Asal mula kata seni dalam bahasa Indonesia tidak begitu jelas dan mempunyai banyak teori, antara lain: Kata seni dari bahasa Melayu Riau (Sungai Rokan) yaitu sonik yang berasal dari kata ‘so’ atau ‘se’ yang memiliki arti ‘satu’, berasal dari bahasa Sanskerta ‘swa’ (satu), yang digabung dengan kata ‘nik’ yang memiliki sesuatu yang sangat kecil atau halus. Kata sonik/sonit/seni artinya suatu yang halus bentuk rupa maupun sifatnya. Kata seni dari bahasa Sansekerta sani yang memiliki arti persembahan, pelayanan dan pemberian yang tulus, sehingga selalu dikaitakan dengan sebuah upacara keagamaan yang disebut dengan kesenian. Kata seni dari bahasa Belanda genie yang berarti genius atau mempunyai kemampuan luar biasa yang dibawa sejak lahir. Jadi dapat disimpulkan bahwa seni itu merupakan kemampuan bakat yang dimiliki seseorang sejak lahir buah dari kejeniusan.",
      "level" : "junior",
      "feature": {
        "rating": 5,
        "users" : 24,
        "age": 6
      }
    },
    {
      "id": 16,
      "group": "course",
      "img": "learn-3.png",
      "title": "Seni Tari",
      "description" : "Melatih siswa untuk menjadi penari yang handal dan juga hafal teknik tertentu dalam seni tari.",
      "category" : "kursus",
      "active": false,
      "text" : "Seni tari bisa dikatakan sebagai bagian dari kebudayaan yang ada pada setiap negara atau daerah termasuk negara Indonesia. Seni tari yang ada di Indonesia sangatlah banyak dan merupakan setiap gerakan tari merupakan ciptaan dari masyarakat Indonesia yang di mana di dalam setiap gerakan tari memiliki filosofinya masing-masing. Seni tari akan selalu mengalami perkembangan seiring dengan berkembangnya zaman. Maka dari itu, bagi sebagian orang mengatakan bahwa seni tari sudah ada sejak lama.<br>Dengan banyaknya seni tari yang ada di Indonesia menandakan bahwa Indonesia memiliki keanekaragaman budaya. Oleh sebab itu, sudah seharusnya bagi setiap masyarakat Indonesia terutama generasi muda perlu melestarikan seni tari Indonesia. Jika, seni tari terus menerus dilestarikan, maka kemungkinan besar seni tari Indonesia semakin dikenal oleh masyarakat dunia.",
      "level" : "junior",
      "feature": {
        "rating": 3,
        "users" : 19,
        "age": 6
      }
    },
    {
      "id": 17,
      "group": "course",
      "img": "learn-2.png",
      "title": "IPS",
      "description" : "Disini siswa akan diajarkan cara untuk mengetahui ilmu sosial dan sejarah indonesia.",
      "category" : "kursus",
      "active": false,
      "text" : "Kata “seni” dalam bahasa Indonesia mempunyai riwayat peristilahan yang tidak sederhana, baik dipandang dari segi terminologis maupun etimologisnya. Hal tersebut mulanya disebabkan karena ketiadaan padanan istilah yang pas dalam bahasa Indonesia/Melayu untuk konsep art dalam bahasa Inggris atau kunst dalam bahasa Belanda. Asal mula kata seni dalam bahasa Indonesia tidak begitu jelas dan mempunyai banyak teori, antara lain: Kata seni dari bahasa Melayu Riau (Sungai Rokan) yaitu sonik yang berasal dari kata ‘so’ atau ‘se’ yang memiliki arti ‘satu’, berasal dari bahasa Sanskerta ‘swa’ (satu), yang digabung dengan kata ‘nik’ yang memiliki sesuatu yang sangat kecil atau halus. Kata sonik/sonit/seni artinya suatu yang halus bentuk rupa maupun sifatnya. Kata seni dari bahasa Sansekerta sani yang memiliki arti persembahan, pelayanan dan pemberian yang tulus, sehingga selalu dikaitakan dengan sebuah upacara keagamaan yang disebut dengan kesenian. Kata seni dari bahasa Belanda genie yang berarti genius atau mempunyai kemampuan luar biasa yang dibawa sejak lahir. Jadi dapat disimpulkan bahwa seni itu merupakan kemampuan bakat yang dimiliki seseorang sejak lahir buah dari kejeniusan.",
      "level" : "junior",
      "feature": {
        "rating": 4,
        "users" : 16,
        "age": 6
      }
    },
    {
      "id": 18,
      "group": "course",
      "img": "materi-4.png",
      "title": "PKN",
      "description" : "Disini siswa akan diajarkan cara untuk menjadi warga negara yang baik dan patuh dengan undang-undang.",
      "category" : "kursus",
      "active": false,
      "text" : "Kata “seni” dalam bahasa Indonesia mempunyai riwayat peristilahan yang tidak sederhana, baik dipandang dari segi terminologis maupun etimologisnya. Hal tersebut mulanya disebabkan karena ketiadaan padanan istilah yang pas dalam bahasa Indonesia/Melayu untuk konsep art dalam bahasa Inggris atau kunst dalam bahasa Belanda. Asal mula kata seni dalam bahasa Indonesia tidak begitu jelas dan mempunyai banyak teori, antara lain: Kata seni dari bahasa Melayu Riau (Sungai Rokan) yaitu sonik yang berasal dari kata ‘so’ atau ‘se’ yang memiliki arti ‘satu’, berasal dari bahasa Sanskerta ‘swa’ (satu), yang digabung dengan kata ‘nik’ yang memiliki sesuatu yang sangat kecil atau halus. Kata sonik/sonit/seni artinya suatu yang halus bentuk rupa maupun sifatnya. Kata seni dari bahasa Sansekerta sani yang memiliki arti persembahan, pelayanan dan pemberian yang tulus, sehingga selalu dikaitakan dengan sebuah upacara keagamaan yang disebut dengan kesenian. Kata seni dari bahasa Belanda genie yang berarti genius atau mempunyai kemampuan luar biasa yang dibawa sejak lahir. Jadi dapat disimpulkan bahwa seni itu merupakan kemampuan bakat yang dimiliki seseorang sejak lahir buah dari kejeniusan.",
      "level" : "senior",
      "feature": {
        "rating": 2,
        "users" : 12,
        "age": 12
      }
    },
    {
      "id": 19,
      "group": "course",
      "img": "learn-1.png",
      "title": "Olahraga",
      "description" : "Melatih siswa agar memiliki raga yang sehat dan imun yang kuat dalam setiap kegiatan.",
      "category" : "kursus",
      "active": false,
      "text" : "Kata “seni” dalam bahasa Indonesia mempunyai riwayat peristilahan yang tidak sederhana, baik dipandang dari segi terminologis maupun etimologisnya. Hal tersebut mulanya disebabkan karena ketiadaan padanan istilah yang pas dalam bahasa Indonesia/Melayu untuk konsep art dalam bahasa Inggris atau kunst dalam bahasa Belanda. Asal mula kata seni dalam bahasa Indonesia tidak begitu jelas dan mempunyai banyak teori, antara lain: Kata seni dari bahasa Melayu Riau (Sungai Rokan) yaitu sonik yang berasal dari kata ‘so’ atau ‘se’ yang memiliki arti ‘satu’, berasal dari bahasa Sanskerta ‘swa’ (satu), yang digabung dengan kata ‘nik’ yang memiliki sesuatu yang sangat kecil atau halus. Kata sonik/sonit/seni artinya suatu yang halus bentuk rupa maupun sifatnya. Kata seni dari bahasa Sansekerta sani yang memiliki arti persembahan, pelayanan dan pemberian yang tulus, sehingga selalu dikaitakan dengan sebuah upacara keagamaan yang disebut dengan kesenian. Kata seni dari bahasa Belanda genie yang berarti genius atau mempunyai kemampuan luar biasa yang dibawa sejak lahir. Jadi dapat disimpulkan bahwa seni itu merupakan kemampuan bakat yang dimiliki seseorang sejak lahir buah dari kejeniusan.",
      "level" : "junior",
      "feature": {
        "rating": 5,
        "users" : 20,
        "age": 6
      }
    },
    {
      "id": 29,
      "group": "course",
      "img": "learn-1.png",
      "title": "Membuat Origami",
      "description" : "Belajar membuat origami dengan cara yang menyenangkan dan kreatif",
      "category" : "modul",
      "active": false,
      "text" : "Kata “seni” dalam bahasa Indonesia mempunyai riwayat peristilahan yang tidak sederhana, baik dipandang dari segi terminologis maupun etimologisnya. Hal tersebut mulanya disebabkan karena ketiadaan padanan istilah yang pas dalam bahasa Indonesia/Melayu untuk konsep art dalam bahasa Inggris atau kunst dalam bahasa Belanda. Asal mula kata seni dalam bahasa Indonesia tidak begitu jelas dan mempunyai banyak teori, antara lain: Kata seni dari bahasa Melayu Riau (Sungai Rokan) yaitu sonik yang berasal dari kata ‘so’ atau ‘se’ yang memiliki arti ‘satu’, berasal dari bahasa Sanskerta ‘swa’ (satu), yang digabung dengan kata ‘nik’ yang memiliki sesuatu yang sangat kecil atau halus. Kata sonik/sonit/seni artinya suatu yang halus bentuk rupa maupun sifatnya. Kata seni dari bahasa Sansekerta sani yang memiliki arti persembahan, pelayanan dan pemberian yang tulus, sehingga selalu dikaitakan dengan sebuah upacara keagamaan yang disebut dengan kesenian. Kata seni dari bahasa Belanda genie yang berarti genius atau mempunyai kemampuan luar biasa yang dibawa sejak lahir. Jadi dapat disimpulkan bahwa seni itu merupakan kemampuan bakat yang dimiliki seseorang sejak lahir buah dari kejeniusan.",
      "level" : "senior",
      "feature": {
        "rating": 5,
        "users" : 4,
        "age": 12
      }
    },
    {
      "id": 30,
      "group": "course",
      "img": "learn-3.png",
      "title": "Menari",
      "description" : "Belajar menari dengan tarian yang indah dan menawan",
      "category" : "modul",
      "active": false,
      "text" : "Kata “seni” dalam bahasa Indonesia mempunyai riwayat peristilahan yang tidak sederhana, baik dipandang dari segi terminologis maupun etimologisnya. Hal tersebut mulanya disebabkan karena ketiadaan padanan istilah yang pas dalam bahasa Indonesia/Melayu untuk konsep art dalam bahasa Inggris atau kunst dalam bahasa Belanda. Asal mula kata seni dalam bahasa Indonesia tidak begitu jelas dan mempunyai banyak teori, antara lain: Kata seni dari bahasa Melayu Riau (Sungai Rokan) yaitu sonik yang berasal dari kata ‘so’ atau ‘se’ yang memiliki arti ‘satu’, berasal dari bahasa Sanskerta ‘swa’ (satu), yang digabung dengan kata ‘nik’ yang memiliki sesuatu yang sangat kecil atau halus. Kata sonik/sonit/seni artinya suatu yang halus bentuk rupa maupun sifatnya. Kata seni dari bahasa Sansekerta sani yang memiliki arti persembahan, pelayanan dan pemberian yang tulus, sehingga selalu dikaitakan dengan sebuah upacara keagamaan yang disebut dengan kesenian. Kata seni dari bahasa Belanda genie yang berarti genius atau mempunyai kemampuan luar biasa yang dibawa sejak lahir. Jadi dapat disimpulkan bahwa seni itu merupakan kemampuan bakat yang dimiliki seseorang sejak lahir buah dari kejeniusan.",
      "level" : "senior",
      "feature": {
        "rating": 5,
        "users" : 20,
        "age": 12
      }
    },
    {
      "id": 31,
      "group": "course",
      "img": "learn-1.png",
      "title": "Ekosistem",
      "description" : "Belajar tentang ekosistem sesuatu dalam alam",
      "category" : "modul",
      "active": false,
      "text" : "Kata “seni” dalam bahasa Indonesia mempunyai riwayat peristilahan yang tidak sederhana, baik dipandang dari segi terminologis maupun etimologisnya. Hal tersebut mulanya disebabkan karena ketiadaan padanan istilah yang pas dalam bahasa Indonesia/Melayu untuk konsep art dalam bahasa Inggris atau kunst dalam bahasa Belanda. Asal mula kata seni dalam bahasa Indonesia tidak begitu jelas dan mempunyai banyak teori, antara lain: Kata seni dari bahasa Melayu Riau (Sungai Rokan) yaitu sonik yang berasal dari kata ‘so’ atau ‘se’ yang memiliki arti ‘satu’, berasal dari bahasa Sanskerta ‘swa’ (satu), yang digabung dengan kata ‘nik’ yang memiliki sesuatu yang sangat kecil atau halus. Kata sonik/sonit/seni artinya suatu yang halus bentuk rupa maupun sifatnya. Kata seni dari bahasa Sansekerta sani yang memiliki arti persembahan, pelayanan dan pemberian yang tulus, sehingga selalu dikaitakan dengan sebuah upacara keagamaan yang disebut dengan kesenian. Kata seni dari bahasa Belanda genie yang berarti genius atau mempunyai kemampuan luar biasa yang dibawa sejak lahir. Jadi dapat disimpulkan bahwa seni itu merupakan kemampuan bakat yang dimiliki seseorang sejak lahir buah dari kejeniusan.",
      "level" : "senior",
      "feature": {
        "rating": 5,
        "users" : 14,
        "age": 12
      }
    },
    {
      "id": 32,
      "group": "course",
      "img": "materi-1.png",
      "title": "Merangkai",
      "description" : "Belajar merangkai suatu ptototype dari seni kerajinan siswa",
      "category" : "modul",
      "active": false,
      "text" : "Kata “seni” dalam bahasa Indonesia mempunyai riwayat peristilahan yang tidak sederhana, baik dipandang dari segi terminologis maupun etimologisnya. Hal tersebut mulanya disebabkan karena ketiadaan padanan istilah yang pas dalam bahasa Indonesia/Melayu untuk konsep art dalam bahasa Inggris atau kunst dalam bahasa Belanda. Asal mula kata seni dalam bahasa Indonesia tidak begitu jelas dan mempunyai banyak teori, antara lain: Kata seni dari bahasa Melayu Riau (Sungai Rokan) yaitu sonik yang berasal dari kata ‘so’ atau ‘se’ yang memiliki arti ‘satu’, berasal dari bahasa Sanskerta ‘swa’ (satu), yang digabung dengan kata ‘nik’ yang memiliki sesuatu yang sangat kecil atau halus. Kata sonik/sonit/seni artinya suatu yang halus bentuk rupa maupun sifatnya. Kata seni dari bahasa Sansekerta sani yang memiliki arti persembahan, pelayanan dan pemberian yang tulus, sehingga selalu dikaitakan dengan sebuah upacara keagamaan yang disebut dengan kesenian. Kata seni dari bahasa Belanda genie yang berarti genius atau mempunyai kemampuan luar biasa yang dibawa sejak lahir. Jadi dapat disimpulkan bahwa seni itu merupakan kemampuan bakat yang dimiliki seseorang sejak lahir buah dari kejeniusan.",
      "level" : "senior",
      "feature": {
        "rating": 5,
        "users" : 10,
        "age": 12
      }
    },
    {
      "id": 33,
      "group": "course",
      "img": "learn-2.png",
      "title": "Menyanyi",
      "description" : "Belajar menyanyi dengan suara yang merdu dan enak untuk didengar",
      "category" : "modul",
      "active": false,
      "text" : "Kata “seni” dalam bahasa Indonesia mempunyai riwayat peristilahan yang tidak sederhana, baik dipandang dari segi terminologis maupun etimologisnya. Hal tersebut mulanya disebabkan karena ketiadaan padanan istilah yang pas dalam bahasa Indonesia/Melayu untuk konsep art dalam bahasa Inggris atau kunst dalam bahasa Belanda. Asal mula kata seni dalam bahasa Indonesia tidak begitu jelas dan mempunyai banyak teori, antara lain: Kata seni dari bahasa Melayu Riau (Sungai Rokan) yaitu sonik yang berasal dari kata ‘so’ atau ‘se’ yang memiliki arti ‘satu’, berasal dari bahasa Sanskerta ‘swa’ (satu), yang digabung dengan kata ‘nik’ yang memiliki sesuatu yang sangat kecil atau halus. Kata sonik/sonit/seni artinya suatu yang halus bentuk rupa maupun sifatnya. Kata seni dari bahasa Sansekerta sani yang memiliki arti persembahan, pelayanan dan pemberian yang tulus, sehingga selalu dikaitakan dengan sebuah upacara keagamaan yang disebut dengan kesenian. Kata seni dari bahasa Belanda genie yang berarti genius atau mempunyai kemampuan luar biasa yang dibawa sejak lahir. Jadi dapat disimpulkan bahwa seni itu merupakan kemampuan bakat yang dimiliki seseorang sejak lahir buah dari kejeniusan.",
      "level" : "junior",
      "feature": {
        "rating": 5,
        "users" : 9,
        "age": 6
      }
    }
  ]
}
